lognostic/__init__.py
lognostic/lognostic.py
lognostic/py.typed
lognostic-0.0.4.dist-info/LICENCE
lognostic-0.0.4.dist-info/METADATA
lognostic-0.0.4.dist-info/WHEEL
lognostic-0.0.4.dist-info/RECORD
