Metadata-Version: 2.1
Name: lognostic
Version: 0.0.4
Summary: lognostic is a lightweight, efficient Python package designed to seamlessly integrate into existing Python applications to provide comprehensive logging statistics. ThiThis package caters to development teams seeking to optimize logging performance, diagnose issues, and understand logging loads without introducing significant overhead or complexity into their applications.
Home-page: https://Mamdasn.github.io/lognostic
License: MIT
Author: Mamdasan Sabrian
Author-email: reach.s.farhad@gmail.com
Requires-Python: >=3.9,<4.0
Classifier: Development Status :: 4 - Beta
Classifier: Intended Audience :: Developers
Classifier: License :: OSI Approved :: MIT License
Classifier: Operating System :: OS Independent
Classifier: Programming Language :: Python
Classifier: Programming Language :: Python :: 3
Classifier: Programming Language :: Python :: 3.9
Classifier: Programming Language :: Python :: 3.10
Classifier: Programming Language :: Python :: 3.11
Classifier: Programming Language :: Python :: 3.12
Classifier: Topic :: Software Development :: Libraries :: Python Modules
Classifier: Typing :: Typed
Requires-Dist: pandas (>=1.3.4)
Project-URL: Documentation, https://Mamdasn.github.io/lognostic
Project-URL: Repository, https://github.com/Mamdasn/lognostic
